{"cameraMode":{"drawMode":0,"name":"Shaded","section":"Shading Mode"},"sceneLighting":true,"audioPlay":false,"sceneViewState":{"m_AlwaysRefresh":false,"showFog":true,"showSkybox":true,"showFlares":true,"showImageEffects":true,"showParticleSystems":true,"showVisualEffectGraphs":true,"m_FxEnabled":true},"in2DMode":false,"pivot":{"x":-5.9589715003967289,"y":-8.901430130004883,"z":8.490004539489746},"rotation":{"x":-0.40515291690826418,"y":0.24948367476463319,"z":-0.11594240367412567,"w":-0.8718907237052918},"size":11.11254596710205,"orthographic":false}